{
  "base_color": {
    "c1": "#2C5261",
    "c2": "#3D8EAD",
    "c3": "#9DC6D7",
    "c4": "#2C5261",
    "c5": "#999999",
    "c6": "#C8BE04",
    "c7": "#DBDBDB",
    "c8": "#6E3D46",
    "c9": "#E9E2E3",
    "c10": "#FF2929",
    "c11": "#F7CAC9",
    "c12": "#73C613",
    "c13": "#2C5261",
    "c14": "#C8BE04",
    "c15": "#222222",
    "c16": "#999999",
    "c17": "#B6B6B6",
    "c18": "#DBDBDB",
    "c19": "#ECECEC",
    "c20": "#F3F3F3",
    "c21": "#FCFBF0"

  },
  "version": 1,
  "timestamp": -1
}